gender_prediction/__init__.py
gender_prediction/gender_prediction.py
src/__init__.py
src/data/__init__.py
src/data/make_dataset.py
src/features/__init__.py
src/features/build_features.py
src/models/__init__.py
src/models/predict_model.py
src/models/train_model.py
src/visualization/__init__.py
src/visualization/visualize.py
trell_ai_gender_prediction-0.0.0.dist-info/DESCRIPTION.rst
trell_ai_gender_prediction-0.0.0.dist-info/METADATA
trell_ai_gender_prediction-0.0.0.dist-info/RECORD
trell_ai_gender_prediction-0.0.0.dist-info/WHEEL
trell_ai_gender_prediction-0.0.0.dist-info/metadata.json
trell_ai_gender_prediction-0.0.0.dist-info/top_level.txt
