Metadata-Version: 2.0
Name: trell-ai-gender-prediction
Version: 0.0.0
Summary: Gender Prediction based on name
Home-page: https://gitlab.com/abhay7/trell-ai-gender-pred
Author: Abhay Kumar
Author-email: abhay@trell.in
License: UNKNOWN
Platform: UNKNOWN
Classifier: Development Status :: 2 - Pre-Alpha
Classifier: Programming Language :: Python :: 3.6
Classifier: Topic :: Scientific/Engineering :: Artificial Intelligence
Requires-Python: >=3.6.9
Requires-Dist: scikit-learn
